{"えっ、お見合い！？": "誒，相親！？", "ピュルテ": "看板", "どうしたのよ、急に。お見合いだなんて": "怎麼了，突然說相親什麼的", "シンデレラ": "仙杜瑞拉", "急でもない。前から考えてはいたのだ": "不突然。我之前就在考慮了", "アデリーナ": "阿德瑞娜", "だってお見合いなんてする理由がないじゃない": "因爲沒有理由去相親啊", "ライメント家は女ばかり。だがお前はプリンセス、プリシラ姉様はあの通り自由な御方。となれば、私がどうにかするほかない": "萊明特家都是女性。但你是公主，普莉希拉姐姐大人又是那樣自由的人。這樣的話，就只能由我來想辦法了", "待ってよ、お義母様も賛成してるの？": "等等，母親大人也贊成嗎？", "きっと賛成して下さる": "一定會贊成的", "じゃあお義母様も知らないの？　そんなのって": "那母親大人也不知道嗎？　這種事", "では、またな": "那，再見了", "ど、どうしよう。えっ、人間さん、追いかけるって言ってくれるの！？　ありがとう、それじゃ急ぎましょう！": "怎，怎麼辦。誒，人，人間君，你說要追上去嗎！？　謝謝，那我們快走吧！", "これでいいんだ。もう私も……": "這樣就好。我也已經……", "（バン！）": "（砰！）", "人間、お前……追いかけてきたのか？　いいんだ、私なら。もう吹っ切れた。お前のおかげだ": "人類，你……追過來了嗎？　沒事的，我。已經想通了。多虧了你", "ちゃんと、普通の男女がすることも経験できた。だからもう、これで割り切ることにした。だって誰かが本当に継がなくては……": "已經好好體驗過普通男女會做的事了。所以，已經決定要這樣了。因爲必須要有人繼承……", "（ガシャーン）": "（哐當）", "今度は何！？": "這次又怎麼了！？", "大変よ、アデリーナ！": "不好，阿德瑞娜！", "シンデレラ！　何か割ったのか？": "仙杜瑞拉！　你打破了什麼嗎？", "わ、私じゃないわよ！　応接間に誰か待たせてたでしょ。その人が魔物に連れて行かれたわ！": "不，不是我！　有誰在接待室等着吧。那個人被魔物帶走了！", "お見合い相手！": "是相親對象！", "森の方に向かったみたいです！": "看起來是往森林那邊去了！", "結局、怖がって逃げちゃいましたね。お見合い相手": "結果，相親對象害怕地逃走了呢", "こういうのも含めて縁がないっていうものよ": "這種事也包括在沒有緣分裏哦", "……やっぱり、こんなの私らしくない": "……果然，這種事不像我", "そうよ、アデリーナ。あなた、家のためになんて我慢してお見合いするような人だったかしら": "是啊，阿德瑞娜。你是爲了家族而忍耐着相親的人嗎", "ありがとう、シンデレラ。人間……お前もな。吹っ切れたと思ってたけど、逆効果だったようだ": "謝謝你，仙杜瑞拉。人類……你也是。我本以爲自己已經想通了，看來是反效果啊", "なんのお話ですか？　って、人間さんもキョトンとしてますけど": "在說什麼呢？　啊，人類君也愣住了", "お前と、あれっきりにしたくなくなった、ということ": "我不想和你，就這麼結束了", "なんだか不穏な空気を感じるわよ": "總覺得氣氛很危險啊", "だから。もう少し、お前と一緒にいさせてほしい": "所以，我想再和你在一起一會"}