{"あら、いらっしゃい。ドロシーさんにクレアさん": "啊啦，歡迎。桃樂絲小姐和克蕾雅小姐", "紫式部": "紫式部", "取材の続きさせてもらおうと思って来ちゃったの。あら、人間さんもいたのね": "我想繼續取材就來了。啊啦，人間君也在呢", "ドロシー": "桃樂絲", "創造期に書いた作品を読みたいって来てくださったんですよね、人間さん": "人間君是想看我創作期寫的作品纔來的吧", "源氏物語っていうんだ？たくさんあるんだね。私も読んでいい？": "是叫源氏物語吧？有很多呢。我也可以看嗎？", "クレア": "克蕾雅", "全巻読もうと思ったら泊まり込みよ": "想要全部看完的話要住在這裏哦", "あの頃は一心不乱にこの物語を書いていましたわ。そうすることで、夫を亡くした哀しみを忘れようとしたんです": "那個時候我一心一意地寫着這個故事。我想通過這麼做，忘記丈夫去世的悲傷", "えっ": "咦", "バサバサバサッ": "嘩啦嘩啦嘩啦", "あ、ちょ、人間さん！？持ってた本、全部落としちゃって、どうしたのよ！大切に扱いなさいよ": "啊，等等，人間君！？你把拿在手上的書全部弄掉了，怎麼了！要小心對待啊", "紫式部って未亡人だったの。てっきり今も人妻なのかと": "紫式部是寡婦啊。我還以爲她現在也是人妻呢", "いいえ？あら、言ってませんでしたっけ": "不是哦？啊啦，我沒說過嗎", "それで？最近は何か書いてるの？": "然後呢？最近在寫什麼？", "今は次の新作のネタを探している最中です": "現在正在尋找下一部新作的題材", "この間の新作『平家くんはもう恋なんてしないと誓ったけど落ちてしまう』も面白かった": "最近的新作《平家君發誓不再戀愛卻還是墜入了愛河》也很有趣", "クレア、もう読んだの！？私、本読むのってすごく時間かかっちゃう……": "克蕾雅，你已經看過了嗎！？我，看書要花很多時間……", "ありがとうございます。平恋は自信作でしたので、嬉しいですわ。ドロシーさんも感想聞かせてくださいね": "謝謝。平戀是我很有自信的作品，能聽到你這麼說我很開心。桃樂絲小姐也請告訴我感想哦", "今度の新作のアイディアは？": "下一部新作的點子呢？", "迷っているんですが、異世界モノにしようかと思っています。ただ既視感ありますよね？どう思います？": "我還在猶豫，不過我想寫異世界題材。但是有既視感吧？你們怎麼看？", "既視感はあるけど、やっぱり異世界モノはまだまだ人気だと思う": "雖然有既視感，但我覺得異世界題材還是很有人氣", "何よ、異世界モノって？": "什麼啊，異世界題材？", "主人公が今いる世界と別の世界に迷い込んでしまうお話で……": "是主人公迷失在和現在所在的世界不同的世界的故事……", "あら、じゃあ人間さんのことじゃない": "啊啦，那不就是人間君嗎", "人間さんが？どういうことですか？": "人間君？什麼意思？", "文字通り、人間さんは人間界からオトギノクニに迷い込んできたから": "就是字面意思，人間君從人界迷失到了童話之國", "まあ！なんてステキなのでしょう！今度の新作は人間さんを題材にさせてください！": "哎呀！多麼美妙啊！請讓我把人間君作爲這次新作的題材！", "タイトル思いついた。『オトギノクニに迷い込んだら平安の美女作家とベストセラー連発することになった』でどう？": "我想到標題了。《迷失在童話之國後和平安時代的美女作家一起創作暢銷書》怎麼樣？", "クレアさん、さすがですわ！タイトルいただきます。今から人間さんのお話、みっちり聞かせてくださいね！": "克蕾雅小姐，不愧是你！標題就用這個了。現在開始請讓我好好聽聽人間君的故事！", "人間さんてばさっきからテンション高いけど、どうしたの。え、紫式部が未亡人だからテンションが上がった？": "人間君從剛纔開始就很興奮，怎麼了。哎，因爲紫式部是寡婦所以興奮了？", "そういえば……私も実はオトギノクニに迷い込んだパターンなんだけど、誰も覚えてないわよねその辺の話": "說起來……其實我也是迷路到了童話之國，但好像誰都不記得這件事呢"}