{"この焼きうどん、美味しい！": "這個炒烏冬麪，好好喫！", "ヴィネ": "維尼", "あー、この海の家って確か、あれやろ？ 有名なうどんの人がプロデュースしてどうこうとか": "啊，這家海之家，我記得是那個吧？ 是那個有名的烏冬麪店老闆策劃的", "ベリアル": "彼列", "そんなに有名なのか。 いや、俺の知り合いなんだけど、それ": "那麼有名嗎？ 不，其實我認識他", "人間さん": "人類君", "実際、こうやって周りのオーダー聞いてても、 焼きそば全然でなくて、みんな焼きうどんにしてるし知名度高いんじゃない？": "其實，像這樣聽周圍的人點單， 也完全沒有人點炒麪，大家都點炒烏冬麪，可見知名度很高吧？", "バエル": "巴耶爾", "む……それって、武蔵はるのさんのことですよね。 人間さんの元カノさんの": "嗚……你說的武藏焰乃小姐， 是人類君的前女友吧", "なんか誤解されてるけど、付き合ったことないぞ。 だから当然、別れてもいないし": "總感覺你誤會了，我們可沒交往過。 所以當然也沒分手過", "むー……そうですか？ その言葉、信じますからね": "嗚……是嗎？我相信你說的話哦", "いや、べっつに兄ちゃんが誰と付き合うとったとか、どうでもええやろ。 ガキちゃうんやから元カレ元カノのひとりやふたり、１０人や２０人、なんたらへんがな": "不，老哥和誰交往又不關我的事。 又不是小孩子了，有個一兩個前男友前女友，甚至十來二十個，又有什麼大不了的", "じゅっ……！？ 元恋人が１０人もいるなんて、あり得るんですか！？": "十……！？ 前男友居然有十個，這有可能嗎！？", "だから違うって！ はるのとは、別に元カノとかじゃないから": "就說不是了！我和焰乃纔不是什麼前女友", "……こんなことばっかり考えて、うっとうしいですよね": "……我老是想這些事，很煩人吧", "いやあ……いまのヴィネくらいなら、別に……。 これで、他の人に迷惑かけたりするなら困るけど……": "不……如果是現在的維妮，倒沒什麼……。 要是給別人添麻煩的話，那就頭疼了……", "そうですよね。 それに、こんなに美味しいうどんを作る人なんだから、 そのことには敬意を払わなきゃいけないし": "也是啊。 而且，人家可是能做出這麼好喫的烏冬麪的人， 我得對他表示敬意纔行", "ほんま、ようやるわ。 そないな男女のもちゃもちゃしたこと、ウチは考えるのも面倒やし。 な、バエル": "真是了不起。 我連去想那些男女之間的事都覺得麻煩。 對吧，巴耶爾", "ふぁんふぇ？ふぉれよりふぉれ、めっふぁ美味ふぃんだふぇど！ （なんて？それよりこれ、めっちゃ美味しいんだけど！）": "呼啊呼欸？呼以呼以，呼以呼以好呼喫呼欸！ （什麼？比起那個，這個超級好喫啊！）", "ただの食いしん坊やん……": "就是個單純的貪喫鬼嘛……"}