{"なぁティンカ……ここオトギノクニは、人の想像や物語が ベースとなった世界なのだろう？ ひとつ、案内してほしい場所があるのだが……ごにょごにょ": "喂，汀可……童話之國是以人的想象和故事爲基礎的世界吧？我想讓你帶我去一個地方……（小聲）", "龍造寺茜": "龍造寺茜", "ふんふん……えぇ、もったいぶらずに教えてよ……ほうほう……あぁ、お菓子の家ね！": "嗯嗯……嗯，別賣關子了，快告訴我……哦哦……啊，糖果屋啊！", "ティンカー・ベル": "汀可貝兒", "声が大きい……！みなに聞かれてしまうではないか！": "你聲音太大了……！會被大家聽到的！", "茜ちゃん、お菓子の家を見に行きたいの？ 言われてみれば、わたしも気になってきた。 タルトタイムの新商品にも活かせるかな？": "小茜，你想去看糖果屋嗎？聽你這麼一說，我也開始感興趣了。 能不能用在塔爾特時間的新商品上呢？", "希咲美桜": "希咲美櫻", "時すでに遅し……もう気づかれているとは……": "已經晚了……已經被發現了……", "いや……茜が甘いもの好きなのはみんな知ってるから": "不……大家都知道你喜歡甜食", "水野貴弘": "水野貴弘", "公然の秘密っていうんだよね〜": "這就是所謂的公開的祕密吧～", "し、仕方ないだろう……！ジョストの練習はもちろん、勉学に剣の鍛錬、 日々活動をすれば自然と糖分が欲しくなるものだ": "沒，沒辦法啊……！喬斯特的練習自不必說，學習和劍術的鍛鍊， 每天活動下來自然會想要糖分", "じゃあ、普段ストイックでいる反動で、スィーツとかの甘いものを食べるの？": "那，你是因爲平時很自律，所以想喫甜食來反衝一下嗎？", "ただ……あの愛らしく華やかな見た目や、甘味だけでない奥深い味わい、 そういったスィーツの持つ魅力も理解しているつもりだ": "只是……那種可愛的華麗外表，以及不僅僅是甜味的深奧味道， 我自認爲也理解了甜食所擁有的魅力", "茜ちゃんはスィーツが純粋に大好きなんだよね。 わたしが作ったお菓子も、美味しそうに食べてくれるし": "小茜是純粹地喜歡甜食呢。 我做的點心，你也會喫得津津有味", "人の食事の様子をつぶさに観察しないでくれっ": "別那麼仔細地觀察別人喫飯的樣子啊", "だって〜、茜ちゃんの幸せそうな顔見ると、作った甲斐があるなって思えるし、 こっちまで幸せな気持ちになるし": "因爲～，看到小茜幸福的表情，我就覺得我做的點心有價值了， 連我都會感到幸福", "そういうことだったらさ、お菓子の家もいいけど……ずきんに色々作ってもらおうよ": "如果是這樣的話，雖然糖果屋也不錯……但還是讓小紅帽做各種各樣的點心吧", "ずきん、といえば……赤ずきんの少女のことか？": "小紅帽，是指……那個小紅帽少女嗎？", "うん、あの子もアップルパイとかのお菓子を作ったり、振る舞ったりするの好きだし": "是的，她也喜歡做蘋果派之類的點心，也喜歡請別人喫", "別世界から来た茜たちにも美味しいって言ってもらえたら、喜ぶと思うよ": "如果來自其他世界的茜你們也說好喫的話，我想她會很高興的", "そうか……ある種の人助けということなら仕方ない。 ぜひ、ご相伴にあずからせてもらおう": "是嗎……如果是某種助人行爲的話，那就沒辦法了。 請務必讓我參加", "誤魔化してるけど、即決してるあたりノリノリだな": "雖然你試圖掩飾，但你立刻就答應了，說明你很感興趣", "ふふ……どんなスイーツを食べさせてもらえるのか…… こちらからリクエストするというのは、少々図々しいだろうか……？": "呵呵……不知道她會給我喫什麼樣的甜品…… 如果我提出要求的話，會不會顯得有點厚臉皮……？", "茜ちゃんたら、もう顔が笑ってるよ〜？": "小茜，你的臉上已經露出笑容了哦～？"}