{"何してるの？　もしかして退屈かしら？": "在幹什麼呢？難道是覺得無聊嗎？", "ヤシャ": "夜叉", "そりゃそうだよなぁ。あたしら４人とだけ、毎日延々だらだらしてりゃなあ": "那也是當然的吧。每天都和我們4個人一起無所事事", "ガンダーヴァ": "乾闥婆", "ヤ、ヤシャと、ガンダは、訓練とか、してる、けど": "夜，夜叉和，乾達，會，訓練，之類的", "キンナラ": "金娜拉", "んでキンナラは一日じゅう読書、と。あれ、何もしてないのってもしかしてマホだけ？": "然後金娜拉整天都在讀書。咦，難道說什麼都沒幹的只有真帆？", "マホラガ": "摩睺羅伽", "い、いいと、思う。マホは、いざというとき、ほ、本気出すし": "我，我覺得，這樣就好。真帆在，緊要關頭，會，拿出真本事", "とにかく、魔獣はいつ来るかわからない。だから備えだけはしておかなくちゃならないの": "總之，不知道魔獸什麼時候會來。所以必須做好準備纔行", "けど、そうそう頻繁に来るわけでもないわ。どうして襲ってくるのか、詳しいことはわからないけど": "但是，也不是那麼頻繁地會來。雖然不知道爲什麼襲擊我們", "前はね、この島もごく普通の平和な島だったんだって": "前段時間，這座島還是個非常普通的和平小島", "けど、あの日から変わっちまった": "但是，從那天開始就變了", "あなたもわかるでしょう。創造期と現在の境目――グランド・リヴィジョンが起きた、あの日から、世界は一変したわ": "你應該也明白吧。創造期和現在的分界線——“大變革”發生後，世界就變了", "ん？　ピンと来てないって顔だけど、グランド・リヴィジョンの瞬間、覚えてないのか？": "嗯？看你一臉沒反應過來的樣子，難道你不記得“大變革”的瞬間嗎？", "ほら、この高台からなら見えるでしょう。あれが迷宮の入口よ。あなたが言うところの十二迷宮ね": "你看，從這個高臺上應該能看到吧。那就是迷宮的入口。就是你說的十二迷宮", "まーね、誰かに正式に頼まれたってわけじゃないよ。『星の魔獣』を抑え込め、なんてね": "是啊，雖然不是正式受人之託。但還是要壓制住“星之魔獸”呢", "けど……それぞれの部族で、一番強いのがマホたちなわけでさ。だったら、マホたちが逃げるわけには、いかないじゃん？": "但是……每個部族裏最強的都是真帆她們。所以，真帆她們不能逃跑吧？", "あたしら八武衆が強くなれたのはさ、それぞれの部族が育ててくれたからなわけだしな。故郷や仲間を見捨てられないだろ？": "我們八武衆能變強，也是因爲有各自部族的培養。不能對故鄉和同伴見死不救吧？", "え？　八武衆なのに４人しかいない、って……う、うん": "呃？明明是八武衆卻只有4個人……呃，嗯", "本来は８人なのよ。ただね……意見が割れてしまって……": "本來是8個人的。只是……意見產生了分歧……", "意見が割れたのは『星の魔獣』の扱いについてよ。完全に滅ぼすべきなのか、それとも……私たちのように、騙し騙しで共存を図るか": "意見分歧是關於“星之魔獸”的處置。是應該徹底消滅，還是……像我們一樣，矇混過關，謀求共存", "こういう問題に、正解はないからね": "這種問題，沒有正確答案呢"}