{"早く女王様にお酒を持ってきなさーい！": "快點把酒端給女王大人！", "ジュリエット": "茱麗葉", "ジュリエット、そんなに大声出したらダメだって。他のお客さんにも迷惑だよ": "茱麗葉，不能那麼大聲說話。會給其他客人添麻煩的", "ロミオ": "羅密歐", "ジュリエットって酒癖悪いんだね": "茱麗葉的酒品真差", "ティンカー・ベル": "汀可貝兒", "……性質の悪い酔っ払いと、可哀想な仲間って思われてそう": "……感覺會被當成性格惡劣的醉鬼和可憐的同伴", "ヴェルメリオ": "威爾梅里奧", "ジュリエットさん、おかわりのお酒を持ってきましたよ。はい、人間さんにはハーブティーです": "茱麗葉小姐，我給你拿酒來了。來，人間君喝的是香草茶", "ピュルテ": "看板", "気が利くわね、ハートのセブン": "你真機靈，紅心7", "え、私はセブン……ですか": "哎，我是7……嗎", "ごくごく……きゅーん！": "咕嘟咕嘟……嗝！", "わ、大変だ！ ジュリエットが倒れた！": "哇，不好！茱麗葉倒下了！", "大丈夫、私の作戦通りよ。ピュルテに強いお酒を持ってこさせて、ジュリエットに飲ませたの。これでしばらく静かだわ": "不用擔心，一切都在我的計劃之中。我讓看板拿烈酒過來，讓茱麗葉喝了。這樣她暫時就會安靜了", "ドロシー": "桃樂絲", "あら、ジュリエットってば寝ちゃったの？": "哎呀，茱麗葉睡着了嗎？", "シンデレラ": "仙杜瑞拉", "あ、姐さん。どこ行ってたの？": "啊，大姐。你去哪兒了？", "あっちこっちの席で、情報収集してたのよ": "我在各個座位上收集情報", "さすがシンデレラさん？ はい！ 人間さん、そうですね☆": "果然厲害，仙杜瑞拉小姐？來！人間君，沒錯☆", "おかげでお酒いっぱいご馳走に……じゃなくて、色々女王エルザのことがわかったわ": "多虧了你，我喝了好多酒……不對，我瞭解到了很多關於女王艾爾莎的事情", "……タダ酒。さすが": "……免費喝酒。果然厲害", "女王エルザの評判は最悪よ。わがまま、横暴、傍若無人、すぐに首をはねるって人々を脅かしているらしいの": "女王艾爾莎的評價非常差。任性，蠻橫，旁若無人，聽說她經常威脅別人說要砍掉他們的腦袋", "え、それって。もしかしてディマイトに感染してたりしない？": "哎，那難道是被惡之力感染了嗎？", "女王エルザは元々そんな性格？ 女王を知っているの？ 人間さん": "女王艾爾莎原本就是那種性格嗎？你認識女王嗎？人間君", "あ、創造期のことね。その頃から性格は変わってないとするなら、ディマイトに感染してるわけじゃあないのね": "啊，是說創造期的事情吧。如果從那時起性格就沒有變的話，那應該不是被惡之力感染了", "……女王エルザがディマイトをばら撒いてる黒幕ってことは？": "……女王艾爾莎就是散佈惡之力的幕後黑手？", "やっぱり、女王エルザのお城には行ってみるべきだね": "果然，應該去女王艾爾莎的城堡看看", "ぷっはー！ 女王様にかんぱーい！": "咕哈！ 爲女王大人乾杯！", "え、な、なに？ いきなり": "哎，怎，怎麼了？ 突然這樣", "すみません、みなさん。ジュリエットの寝言みたいです": "對不起，各位。茱麗葉好像在說夢話"}