{"紫の、じゃない。ノティティアだよ。名前": "不是紫色的。我是诺蒂蒂亚。这是我的名字", "ノティティア": "诺蒂蒂亚", "あ、ごめん、つい": "啊，抱歉，一不小心", "ティンカー・ベル": "汀可貝儿", "あの神殿はどんな場所なんですか？": "那个神殿是个什么样的地方？", "ピュルテ": "看板", "人間界から供給されるイメージを、あの神殿で調整しながらオトギノクニへ還元してるんだ": "人类世界提供的形象，会在那个神殿里进行调整，然后还原到童话之国", "デュクス": "杜克司", "イメージを調整？": "调整形象？", "シンデレラ": "仙杜瑞拉", "文明レベルが違うから": "因为文明等级不同", "人間界のイメージそのままだと、世界に歪みが生じてしまうんだ。だから純粋なエネルギー体、つまりエルマイトに変換してる": "如果直接还原人类世界的形象，世界会产生扭曲。所以要转换成纯粹的能量体，也就是圣之力", "ふうん。そのへん手を入れてるわりには、ディマイトのバランスが崩れてるんじゃない？": "嗯。明明做了这么多调整，恶之力的平衡还是崩坏了？", "ドロシー": "桃樂絲", "だってあれは神殿を通らないで、オトギノクニに直接……": "因为那个没有通过神殿，而是直接传送到童话之国……", "喋りすぎよ、デュクス": "你话太多了，杜克司", "ユスティ": "尤斯提", "うあっ、ユスティ！　いつのまに！": "呜哇，尤斯提！你什么时候来的！", "ちょっと目を放すとすぐこれなんだから。ノティティアの無口を少しは見習ってちょうだい": "一不注意就变成这样了。你倒是学学诺蒂蒂亚的沉默寡言", "いま褒められた？": "刚才被夸奖了吗？", "あんまり褒められてないから喜ばない方がいいよ": "没有被夸奖，所以还是不要高兴比较好哦", "アイテムもそこそこ集まったようね。では神殿に戻りましょう": "道具也收集得差不多了。那么我们回神殿吧"}