{"ひょんなことから出会ったシェイファーに猛烈な求愛をされてしまう人間さん。満更でもないようすにずきんもやきもき。": "人間君被因緣際會相遇的謝法猛烈地求愛。頭巾也對人間君一副不討厭的樣子感到焦躁。", "そんな折、死神・メッソーレムが起こしたアケローン川事件を収めるため、シェイファーは冥界に戻ることに。": "就在這時，爲了平息死神梅索雷姆引發的阿凱隆河事件，謝法決定返回冥界。", "シェイファーが差し出した手を、人間さんは取るのか——": "人間君會握住謝法伸出的手嗎——", "ね。冥界に戻ったらもうこっちに来られないから。人間さんが一緒なら寂しくない": "人間君。回到冥界之後我就再也來不了這裏了。如果人間君能一起來的話，我就不會寂寞了", "シェイファー": "謝法", "そ、それは困ります！だって人間さんには、こっちの世界のディマイトを抑えてバランスを……あれ、バランス？": "那，那可不行！因爲人間君要抑制這邊世界的惡之力，保持平衡……咦，平衡？", "ピュルテ": "看板", "……あっ、人間さん。シェイファーの手を……握った！行っちゃうの！？": "……啊，人間君。握住了……謝法的手！要走了嗎！？", "ヴェルメリオ": "威爾梅里奧", "待って、みんな。シェイファーの目元からあれ": "等一下，大家。謝法的眼角有那個", "シンデレラ": "仙杜瑞拉", "へへ、泣いちゃダメだよね。でも選んでくれたこと、嬉しかった。ずっと忘れないよ": "嘿嘿，不能哭出來呢。但是你選擇了我，我很高興。我永遠不會忘記的", "えっ、人間さんの手を振り払って冥界へ！？シェイファー！": "誒，人間君甩開手要回冥界了！？謝法！", "ドロシー": "桃樂絲", "あはは、やった！やり返してやったわ、これでシェイファーは永遠に冥界に": "啊哈哈，好耶！報了一箭之仇，這下謝法就永遠回不了冥界", "アヴァリ": "阿瓦里", "とんだお涙頂戴の茶番だったね。さて、人間さん以外はきみたちもまとめて冥界へ……うっ、うああっ！？な、なんだこの感覚はっ！": "真是一出賺人熱淚的鬧劇。好了，除了人間君以外，你們也一起回冥界……嗚，嗚啊啊！？這，這感覺是怎麼回事！", "メッソーレム": "梅索雷姆", "またあんたのそのオーバーな演技……って、違うわ、本当に周りが！": "你又在演戲……不對，是真的周圍！", "シェイファーさんが戻ったことでバランスが修正されて、死神さんのパワーが抑制されたんです。シェイファーさん……": "謝法先生回來後平衡被修正，死神先生的力量被抑制了。謝法先生……", "……じゃあ、本当は人間さんも一緒に行くべきだったのかな。わたしがワガママ言ったから": "……那，其實人間君也應該一起去的吧。都怪我任性", "違うと思います。バランスなんです。人間さんまで行ったら偏りすぎてしまうかもしれません": "我覺得不是。是平衡的問題。如果人間君也去了，可能會太偏", "……え、じゃあ、シェイファーは最初から連れて行くつもりなんかなかったの": "……誒，那，謝法從一開始就不打算帶我去嗎", "おねえちゃんは、自分のエルマイトを高めるために楽しい思い出いっぱい作ろうとしてたんだと思います": "我覺得姐姐是爲了提高自己的聖之力，纔想創造很多快樂的回憶", "グース": "古斯", "それで人間さんと……？え、待って、それじゃシェイファーは最初からこうして別れることになるの分かってたの！？": "所以才和人間君……？誒，等等，那謝法從一開始就知道會這樣分別嗎！？", "はい。けど、お姉ちゃんは本当に人間さんのこと好きになって……きっと辛かったはずです……": "是的。但是，姐姐真的喜歡上了人間君……她一定很痛苦……", "くうっ、ボクを差し置いて好き勝手するじゃないか。このくらいでボクを倒せると思ってもらっちゃ困るな": "咕，居然把我放在一邊自作主張。別以爲這樣就能打倒我", "いけない、話は後。来るわよ！": "不行，之後再說。要來了！"}