{"あれは……コールサック": "那是……火山灰车站", "ブルカニロ博士": "布鲁卡尼罗博士", "なんだか暗い駅ですね": "总感觉这个车站很阴暗", "ピュルテ": "看板", "……怖い": "……好可怕", "ヴェルメリオ": "威尔梅里奥", "コールサックは死者が住まうと言われている場所だから": "据说火山灰车站是死者居住的地方", "ザネリ": "萨涅利", "空に開いた深い孔だよね": "是一个在天空中打开的深洞", "私、降りなきゃ": "我必须下车", "カンパネルラ": "卡帕涅拉", "ちょっと待ってよ！なぜ降りるの？": "等等！为什么下车？", "ジョバンニ": "乔万尼", "な、なに、どうしたの": "怎，怎么了，发生什么了", "ドロシー": "桃樂絲", "コールサックが私の目的地だから": "火山灰车站就是我的目的地", "こんな暗くて怖い場所に、何の用事があるっていうのさ": "这么阴暗恐怖的地方，到底有什么？", "ねえねえ、さっきから誰と話してるの？": "喂喂，你从刚才开始就在和谁说话？", "ティンカー・ベル": "汀可贝儿", "え？誰って……カンパネルラだよ": "咦？和谁……卡帕涅拉啊", "カンパネルラですって？！どこ？！": "卡帕涅拉？！他在哪？！", "あなた、当て付けでそんなこと言って、そこまでわたしを嫌ってるの？": "你故意这么说，是想惹我生气吗？你就这么讨厌我吗？", "え？みんな、何言ってるの？カンパネルラはさっきからあたしの隣にいるじゃない！": "咦？大家在说什么？卡帕涅拉从刚才开始就一直在我身边啊！", "誰もいないけど？": "没有其他人啊？", "クレア": "克蕾娅", "ジョバンニはさっきから、誰もいない空間に話しかけてるよぉ？": "乔万尼从刚才开始就在和空无一人的空间说话哦？", "エミリー": "艾蜜莉"}