{"ダングラールからの依頼、どんな内容だった。引き受けたのかい": "丹格拉爾的委託，是什麼內容。你接了嗎", "トレローニー": "託雷羅尼。", "すごくお世話になった人たちが、グラン＝ドミング島まで行きたいらしいよ。報酬も弾んでくれたし、ひとっ飛びしようかなって": "他好像想帶非常照顧他的人去格蘭・多米尼克島。報酬也給得很豐厚，所以我想飛一趟", "ホーキンズ": "霍金斯", "ダングラールって誰だっけ？": "丹格拉爾是誰來着？", "シルバー": "銀", "ほら、レスラーの。エディ・ダンテスとこのまえ試合してたでしょ": "就是雷索萊的。之前不是和艾迪・丹特斯比賽過嗎", "その客はグラン＝ドミング島へ何をしに行くのだろう": "那位客人去格蘭・多米尼克島做什麼呢", "やっぱりアレじゃあないかな。宝……": "應該還是那個吧。寶……", "お宝だよね！グラン＝ドミング島にはまだまだいっぱい金銀財宝が隠されてるってウワサだもん。ねえ、あたしたちもしようよ、宝探し☆": "是寶藏吧！聽說格蘭・多米尼克島上還藏着很多金銀財寶呢。吶，我們也去尋寶嘛☆", "私たちまで宝探しに！？": "我們也去尋寶！？", "あたしも新しい食材を調達したいし！ヒスパニオラ号じゃないと採れない食材っていっぱいあるんだよ。どう、トレローニー": "我也想採購新的食材！有很多食材只有伊斯帕尼奧拉號才能採到。怎麼樣，託雷羅尼。", "私は飛べるならどっちでもいいよ": "我只要能飛去哪裏都行", "賛成多数で宝探し決定☆いいよね、ジェミ": "多數贊成，決定去尋寶☆可以吧，傑米", "どっちでもいいって言ったんだから全然多数じゃないでしょ！でも、最近ちょっと冒険してなかったし、それもいいかな": "你不是說去哪裏都行嗎，這哪叫多數贊成啊！不過，最近確實有點缺乏冒險，這樣也不錯", "やったぁ☆ねえ、じゃあさっそく準備しに町に買い物行こう〜！": "太好了☆那我們趕緊去鎮上採購，做好準備吧！"}