{"オトギノクニ最大の音楽イベントオトギストック。": "童話之國最大的音樂活動童話stock。", "その最終日に行われるコンテストファイナルは、かつて同じバンドにいながら決別した者たちの戦いとなった。": "在最後一天舉行的決賽，成爲了曾經同在一個樂隊，卻決裂的成員們的戰鬥。", "プロデューサーとして招かれた人間さんは、対立する彼らの間を奔走。": "作爲製作人被邀請的人類君，在對立的他們之間奔走。", "そして今、まさに決戦の結果が明らかになろうとしていた——": "而現在，決戰的結果即將揭曉——", "今夜っ、おまえたちはここで伝説を再び目にする！聞けぇ、我の魂の叫びを！": "今晚，你們將在這裏再次見證傳說！聽吧，我靈魂的吶喊！", "ケーシ": "凱西", "ワアアアア！！": "哇啊啊啊啊！！", "人間さん！お疲れ様です、大変でしたよね": "人類君！辛苦了，很不容易吧", "ピュルテ": "看板", "……でもコンテストも無事に終わってよかった": "……不過比賽能順利結束真是太好了", "ヴェルメリオ": "威爾梅里奧", "でもこれって勝敗なんか決められるのぉ？みんな音楽の雰囲気違うし、めちゃくちゃ上手かったし": "但是這個能決定勝負嗎？大家的音樂氛圍都不一樣，而且都超厲害的", "エミリー": "艾蜜莉", "ケーシさんのダサいMCとかホッとしちゃいますけどね": "凱西的土氣MC倒是讓人鬆了口氣", "……勝敗は会場のお客さんが投票するんだよね": "……勝負是由會場的觀衆投票決定的吧", "あっ、このボタン？じゃあエミリーも押せるんだ。ええ〜、でも決められないよぉ": "啊，這個按鈕？那艾蜜莉也能投票了。誒誒，但是決定不了啊", "締め切り時間が迫ってますよ！っていうか、迷うなら人間さんがプロデュースしたイロハさんたちにしましょうよ！": "截止時間快到了！話說，猶豫的話就投人類君製作的伊呂波她們吧！", "あっ、それもそうだね！": "啊，說的也是！", "…………。": "…………。", "それではいよいよ、結果発表ーっ！正面のモニターにご注目ください！会場の３万人の投票先はいかにっ！": "那麼，終於到了公佈結果的時候了！請看正前方的屏幕！會場的三萬人會把票投給誰呢！", "司会": "主持人", "あの人、ナイスルッキングの人だぁ": "那個人，是喜歡看別人的人啊", "BeB：13715票、カラカノ：14162票、ケーシ：2623票ということで僅差でカラカノの優勝です！": "BeB：13715票，卡拉卡諾：14162票，凱西：2623票，卡拉卡諾以微弱優勢獲勝！", "えっ……！？そ、そんな馬鹿な！優勝できないまでも、に、二千！？": "誒……！？怎，怎麼可能！就算不能獲勝，也，也該有兩千票吧！？", "みんな！おつかれ": "大家！辛苦了", "イロハ": "伊呂波", "うん、ちょっと悔しいけど、でもライブ楽しかった……": "嗯，雖然有點不甘心，但演唱會很開心……", "サラスヴァ": "薩拉斯瓦", "最高だったよね": "真是太棒了", "ヴァイシュラ": "瓦伊休拉", "ふふん、なかなかいい勝負でしたね": "嗯哼，真是場不錯的比賽", "マハー": "瑪哈", "おめでとう！あんたたちも、最高にカッコよかった": "祝賀你們！你們也是最帥的", "えへへ、ありがとー！": "嘿嘿嘿，謝謝！", "マスクドマカシ": "假面真打", "盛り上がったんだなーっ！": "熱烈的氣氛啊！", "バザラ": "巴沙拉", "な、なんですか。素直に称賛とか、調子が狂います": "你，你幹什麼。這麼坦率地稱讚我，我都不知道怎麼反應了", "あたしは音楽では嘘つかない主義なもんで": "我的原則就是音樂不撒謊", "うあああ！何故、何故なんだ！我の音楽は理解されないのか！": "嗚啊啊啊！爲什麼，爲什麼啊！我的音樂不被理解嗎！", "ちょ、ちょっとケーシ！いきなりギター持ってどうするつもり！？": "等，等一下凱西！你突然拿着吉他幹什麼！？", "我の音を、ギターを、聞けええぇぇぇっ！": "聽我的音樂，聽我的吉他吧啊啊啊啊啊！", "どうしたんだろう、急にギター弾き始めたよ。即興かな": "怎麼回事，突然彈起了吉他。即興演奏嗎", "……ねえ、ピュルテ。この音色、もしかして": "……喂，看板。這個音色，難道是", "ええ！サウンドにディマイトが乗っています！": "是的！聲音裏有惡之力！"}