{"オレが何したっていうんだよ！　ただ美味いラーメン作ろうとして、それだけだろ！": "我到底做了什么啊！ 我只是想做美味的拉面，仅此而已啊！", "柳生みつ": "柳生光", "それがいけないのです。心頭滅却すれば大豆もまた肉になる": "就是这一点不行。只要灭却心头火自凉，大豆也能变成肉", "修行僧": "修行僧", "いやそれ、畑の肉っていう、ただの例えだからね！": "不不，那只是比喻田里的肉而已啦！", "ティンカー・ベル": "汀可贝儿", "む……あなたたちは": "呜……你们是", "『二天うどん』の店主、武蔵はるのよ！　柳生から離れて！": "我是“二天乌冬面”的店主，武藏野！ 从柳生身边离开！", "武蔵はるの": "武藏野", "はるの先輩！　ごめん、オレ……": "萤火前辈！ 对不起，我……", "わたしもこれ以上は見過ごせませんね。ただ飲食店をやっているだけで取り囲んで罵るとは、明らかにやりすぎでしょう": "我也无法再坐视不管了。仅仅因为经营餐饮店就被包围辱骂，这明显是过火了吧", "佐々木さん": "佐佐木", "のめりこんじゃった人は家に帰らないって聞くし、何が目的なの！？": "我听说沉迷的人是不会回家的，你们到底有什么目的！？", "確かに食べ過ぎれば太っちゃったりとか、健康に悪いこともあるだろうけどそれ自体が毒じゃないんだから！": "虽然确实吃太多的话会变胖，对健康也不好，但面类本身并不是毒药啊！", "あなたは食べすぎだと思いますけどね。下っ腹、大丈夫ですか？": "我倒是觉得你吃太多了。小腹，没问题吗？", "出てないわよ！": "没凸出来啦！", "シンデレラ": "仙杜瑞拉", "姐さんに言ってないから！": "我没对姐姐说啦！", "栄養が全部、胸にいってるんだろ": "营养全都跑到胸部去了吧", "ひどーい！　それおバカな子に使われるやつだよ！": "太过分了！ 这是用在笨蛋身上的说法啦！", "食欲は抑えなくてはならない。特に麺類は厳禁": "必须抑制食欲。特别是严禁面类", "なんで麺類って指定するのよ": "为什么指定面类啊", "それがアザ様の教えなのだ": "这是阿萨大人的教诲", "えっ、アザ様って……うそ、まさか……": "啊，阿萨大人是……骗人，难道是……", "坊主のわんちゃん。脱走してラーメン食べにいった駄犬はちゃんと捕獲できたのかしら？": "小和尚。逃走跑去吃拉面的笨狗有好好抓回来吗？", "アザ": "阿萨", "はい、ここに": "是的，在这里", "やっぱり！　あなただったのね！": "果然！ 就是你啊！", "んー？　このわんちゃん、なんだっけ？": "嗯？ 这只小狗，怎么了？", "麺の町に、突如おとずれた謎の高い意識。": "面类小镇，突然造访的谜之高意识。", "その正体は、剣の道を諦めた原因である悪魔だった――！": "其真面目，正是让她放弃剑道的恶魔——！", "再び剣を振ることはできるのか。": "她还能再次挥剑吗。", "次回『みんな一緒にガマンして！欲望の悪魔　アザ』": "下一回『大家一起忍耐！欲望的恶魔　阿萨』"}