{"あ、あたし……？": "我，我……？", "鬼島うらら": "鬼島うらら", "もう大丈夫。人間さんがディマイト中和してくれたから、心配いらないよ": "已經沒事了。人類君中和了惡之力，不用擔心了", "吉備津桃葉": "吉備津桃葉", "中和って……え、ディマイト……？": "中和……誒，惡之力……？", "くっそ、マッシュもポイポイもやられちまったか……完璧だったはずの俺の計画が……！": "可惡，馬修和小P也被幹掉了……我的完美計劃……！", "バイメン": "拜門", "わりとあんた、自分で計画ダメにしてた気がするんだけど": "我覺得是你自己把計劃搞砸的", "浦島みずえ": "浦島みずえ", "はい、これ付けて": "來，戴上這個", "金蘭": "金蘭", "う、うん……ありがとう……": "嗯，嗯……謝謝……", "あっ、なんで付けちゃうんだ。絶対、外してたほうがいいって": "啊，爲什麼要戴啊。絕對還是不戴比較好", "余計なこと言うな！　そうそう、人間さんの言うとおり、外見に惑わされる男にろくなやつはいないんだから": "別多嘴！對對，人類君說得對，被外表迷惑的男人肯定不是什麼好東西", "でも人間さんくんも、外した後の方が微妙にうららに優しくなってるような……": "但是人類君在摘掉眼鏡後好像也微妙地對小uraura溫柔起來了……", "フアナ": "弗亞納", "くううっ、メガネと同じで、外した瞬間に美人だとわかるパターンだったか……失敗した……": "咕嗚嗚，和眼鏡一樣，是摘掉的瞬間就能看出是美女的類型嗎……失敗了……", "あたしはメガネかけたままで美人だよ！": "我戴着眼鏡的時候也是美女哦！", "自分で言い切っちゃったよ": "自己斷言了啊", "なあたのむ、うらら。やり直そう！　なっ？": "求你了小uraura。我們重來吧！好嗎？", "まーくん……": "阿真……", "うららちゃん、こいつはまーくんじゃないの。魔物なんだよ。ていっ！": "小uraura，這傢伙不是阿真。是魔物啊。嘿！", "いでぇっ！？　あっ、変化の術がっ": "好痛！？啊，變化之術", "……えっと、魔物はちょっと……": "……那個，魔物有點……", "――っ！？　この俺が、フラれたぁぁぁっ！？": "——！？我被甩了！？", "あ……！　あ、あたし、人生で初めてフッたかも！": "啊……！我，我可能是人生第一次甩人！", "やるじゃん。一歩、成長だよ": "不錯嘛。成長了一步哦", "もう……今までのあたしとはさよならだね。これも……せぇいっ！": "已經……和至今爲止的我告別了呢。這個也……嘿！", "スホマを叩き折った！？　構造的にそれ、折れるものなの！？": "手機被折斷了！？從構造上來說，那是能折斷的東西嗎！？", "そんなに難しいことじゃないと思うよ。折れる、折れる": "我覺得沒那麼難哦。折斷，折斷", "そんなことしなくてもデータ消せばいいんじゃ……": "不用做那種事，把數據刪掉不就好了……", "いいの。心機一転、新しく買うから。さっき、角にお店あったし": "不用啦。我要轉換心情，買支新的。剛纔在街角有看到店家", "じゃあ、生まれ変わった記念に、一杯いっとく？": "那爲了紀念你脫胎換骨，要不要喝一杯？"}