{"みなさんのドレスも素敵ですわね。私、このドレスでいいか、だんだん迷い始めてしまいましたわ": "大家的禮服也很漂亮呢。我開始猶豫，自己是不是也該穿這件禮服了", "シャルロッテ": "夏綠蒂", "デザインも素敵だし、よく似合ってると思うよ？　あ、これは恩返しのお世辞とかじゃなく本心": "設計也很棒，我覺得很適合你哦？　啊，這不是報恩的客套話，是真心話", "セクス": "性愛", "ねえ、このドレス……シンデレラのお古なんだっけ？　どうみても新品なんだけど、本当にもらってもいいの？": "話說，這件禮服……是仙杜瑞拉的舊衣服吧？　怎麼看都是新衣服，我真的可以收下嗎？", "ベートーヴェン": "貝多芬", "シンデレラはプリンセスだから、いろんなメーカーからサンプルが届くのよ": "因爲仙杜瑞拉是公主，所以有很多廠商會送樣品給她哦", "ドロシー": "桃樂絲", "着てもらえれば、それだけで宣伝になりますものね": "只要她願意穿，光是這樣就能成爲宣傳了呢", "だからってウェディングドレスばっかり、こんなにあってもねえ": "但就算這樣，婚紗也太多了吧", "シンデレラも、眠ってるドレスたちが日の目を見れるって喜んでたわよ": "仙杜瑞拉也說，沉睡的禮服們能重見天日，她很高興哦", "あら、おかえりなさい。人間さん": "啊啦，歡迎回來。人類君", "シンデレラ、ちゃんと馬車に乗れた？　いつも通り、だいぶ酔ってたから……": "仙杜瑞拉，有好好坐上馬車嗎？　她跟往常一樣，暈得很厲害……", "人間さん、その赤い封筒なんですの？": "人類君，那個紅色信封是什麼？", "赤い封筒……？": "紅色信封……？", "帰り道で拾った？　中にお金とネックレスが入ってるですって！？　儲けたわね！": "是在回來的路上撿到的？　裏面裝着錢和項鍊！？　賺到了呢！", "落とし主が探してるね。そして恩返ししたくてウズウズしていると思うよ": "失主應該在找吧。而且我想，他應該正躍躍欲試地想要報恩呢", "あ、う、うん、そうよね。私もそう言おうと思って……": "啊，嗯，嗯，是啊。我也正想這麼說……", "ダダダダーン！　思い出した！　赤い封筒！　なんというフキツ！！": "嘟嘟嘟嘟——！　我想起來了！　紅色信封！　多麼殘酷！！", "大声でどうしたんですの？": "怎麼突然大喊大叫起來了？", "その封筒は結婚式の招待状だよ、人間さん": "那個信封是婚禮的邀請函哦，人類君", "結婚式？": "婚禮？", "そう――死者とのね！": "沒錯——是和死者的婚禮！"}