{"さあ、ここはヘンゼルとグレーテルのお菓子の家よ。せっかくだからここでお菓子作りに挑戦していってね": "来，这里是汉赛尔和格莱特的糖果屋哦。机会难得，就在这里挑战一下制作点心吧", "シンデレラ": "仙杜瑞拉", "お菓子ですかぁ……♪　はわぁ……楽しみですぅ……": "点心吗……♪ 哇啊……好期待……", "シャルティーナ": "夏洛蒂娜", "よし、やってみるか。ここでがんばって、エルゼのやつに差をつけてやる": "好，试试看吧。在这里努力一把，拉开和艾尔泽那家伙的差距", "キュンキュン": "裘丘", "エルゼ？　あ、今回は来てない他のお仲間もいらっしゃるんですよね": "艾尔泽？ 啊，这次还有其他没来的伙伴对吧", "ピュルテ": "看板", "直前に理事長から試験があったの。その上位６名が参加することになったのよ": "前几天理事长组织了考试。考试前6名的人参加这次活动", "鷲宮 鷹美": "鹫宫 鹰美", "まあその試験っていうのも、お察しのとおりアレなものだから……上位っていっても優秀とかではないんだけど": "虽然那个考试，正如你所想的那样……说是前6名，其实也不是很优秀啦", "夢ヶ崎 魔恋": "梦崎 魔恋", "はい、ここまでの流れでなんとなく分かる気がします。キュンキュンさんは、エルゼさんがライバルなんですか？　今回いなくて寂しいのでは？": "嗯，从之前的流程来看我大概也猜到了。裘丘小姐，艾尔泽小姐是你的劲敌吗？ 她这次没来，你是不是很寂寞？", "はっ、まさか。私の方が上だってわからせるチャンスだと思ってるのだがっ": "哈，怎么会。我倒觉得这是个让她知道我更厉害的机会", "…………………………。": "…………………………。", "ふぅ……これであとはオーブンに入れるだけです……上手にできているといいのですが……": "呼……接下来只要放进烤箱就好了……希望做得好……", "シャルティーナさんはケーキを焼いたのね。私はマカロンですわ": "夏洛蒂娜同学烤了蛋糕啊。我做的是马卡龙", "ロザリナ": "罗莎莉娜", "お菓子の魔女、ペリーヌ先生の指導はとても分かりやすかったわね": "点心魔女佩利奴老师的指导非常易懂呢", "♪": "♪", "ペリーヌ": "佩利奴", "『私を食・べ・て♪　甘くてほろ苦いキュンキュン・チョコレート』": "『吃・掉・我♪ 甜甜微苦的怦然心动・巧克力』", "うあああっ！？": "呜啊啊啊！？", "しまった、チョコレートソースをひっくり返して、体がチョコまみれに……お、おい、崎羽！？": "不妙，巧克力酱打翻了，身上都是巧克力……喂，喂，崎羽！？", "俺のためにチョコを作ってくれたのか、キュンキュン……！　いただきます！": "你为了我做了巧克力吗，怦然心动……！ 我开动了！", "崎羽 精炎": "崎羽 精炎", "あ、や、やめろっ、んんっ、舐めるんじゃないっ、そこはチョコじゃなくて、はぁっ、私の肌だっ……！": "啊，住，住手，嗯嗯，不要舔，那里不是巧克力，哈啊，是我的肌肤……！"}