{"ここは……何かの遺跡ですわね": "这里是……某种遗迹呢", "シャルロッテ": "夏绿蒂", "例の、幻の鳥を祀った祭壇だよ……。その昔、ディマイトが強くなり暴れた鳥の怒りを鎮めるために作られたの……": "是祭祀幻之鸟的祭坛哦……很久以前，为了平息恶之力变强而发狂的鸟的愤怒而建造的……", "ラビィ": "拉比", "って設定でどうかな……。たまたまクルージングに組み込まれてた観光スポットだけど、結構雰囲気あるし": "这个设定怎么样……虽然只是偶然被安排在巡航路线上的观光景点，但气氛还是挺不错的", "みんながおっぱいをアピールすることで、やっぱり巨乳は女の子についててなんぼ……と人間さんが思えば、鳥の怒りは鎮まり願いはキャンセルされる": "大家通过展示奶子，让人类君觉得果然女孩子就是要长着巨乳……鸟的愤怒就会平息，愿望也会被取消", "鳥の怒り……？　昨日の話から方向がだいぶ変わってきているような……": "鸟的愤怒……？　感觉和昨天的话题方向差很多呢……", "アリス・ミルズ": "爱丽丝・米尔兹", "おっぱいのアピールって何よ。ヌードにでもなれっていうの？": "展示奶子是什么意思啊。难道要我们脱光吗？", "竜宮　あき": "龙宫　明", "だ、だめだめ、それは垢バ……じゃない、かえって怒りを買うから……。セクシーなポーズとか、色々あるでしょ": "不，不行不行，那样会封号……不对，反而会惹怒他……还有性感的姿势之类的，有很多方法吧", "人間さん、アピールされてなくても自分の体におっぱいはいらないと思ってるそうですが……": "人类君好像觉得就算不展示奶子，自己的身体也不需要奶子……", "みなみ": "南", "消えていない、ということは、本気ではないから……では？": "没有消失，也就是说，他不是认真的……是这样吗？", "本気じゃない、か。さっき揉みまくってたもんねぇ……": "不是认真的吗。毕竟刚才揉得那么厉害呢……", "ティンカー・ベル": "汀可贝儿", "わかりましたわ！　私のセクシーアピールで人間さんを変えてみせますわ！": "我明白了！就用我的性感展示来改变人类君吧！", "人間さんさ～ん♪　一緒にお散歩しましょうですわ～": "人类君～♪我们一起散步吧～", "腕を組んで胸を押し付ける作戦……いろんな意味でベッタベタですね。シャルロッテ様": "把手臂挽在一起把胸部贴上去的作战……在各种意义上都很老套呢。夏绿蒂大人", "こんなのはいかがです？　はい、人間さん、アイスキャンディをどうぞ。あ～んして♪": "这样如何？来，人类君，这是冰棒。啊～♪", "なっ……！？　谷間に棒付きアイスを挟んで食べさせるなんて……！　熟練の技だわ": "什……！？居然把带棒的冰棒夹在乳沟里喂他吃……！真是熟练的技巧", "え、え、え、私はどうすればっ……。というか、私には無理で……あっ！": "啊，啊，啊，我该怎么做……话说，我做不到……啊！", "ディアトロン": "迪亚多伦", "ごごごごごごめんなさい、人間さん！　転んで、おっぱいの下敷きにしちゃいました……！": "对对对对对对不起，人类君！我摔倒了，胸部压到你了……！", "悔しいを通り越して感動したよ、ティンカ": "已经超越不甘心，我感动了，汀可", "まだ人間さんのおっぱいは消えていない。……もっとです": "人类君的胸部还没有消失……再来", "えっ？　わ、私はこういうのはちょっと……": "哎？我，我对这种有点……"}