{"いらっしゃいませー！　あ、人間さん。どうしたの、お店になんて来てくれて。うん、今度のバーベキューね！　すっごく楽しみ！！": "歡迎光臨！啊，人類君。怎麼了，居然來店裏了。嗯，下次的BBQ對吧！我非常期待！！", "武蔵はるの": "武藏春乃", "え……もし仮に万一天変地異とかでキャンセルになったら？": "哎……如果萬一因爲天地異變之類的取消了呢？", "バァァァン！": "砰！", "しょうがないんじゃない……？　この２か月くらいの私の心の支えだったから……すごく落ち込むけど……！": "那也沒辦法吧……？因爲這兩個月來，這都是我心靈的支柱……雖然會非常失落……！", "別に……これ、うどん打ってるだけだから気にしないで……": "沒什麼……這只是在擀烏冬麪而已，別在意……", "あっ、ごめんごめん、そうだよね、仮の話だもんね！　そんなことないよね！": "啊，抱歉抱歉，也是呢，只是假設嘛！不會那樣的吧！", "あ……やっぱりね……。私なんかの誘いを人間さんが受けるわけないと思ってた……うまくいきすぎてると思ったんだよね……": "啊……果然……我就知道人類君不可能接受我的邀請……我就覺得事情進展得太順利了……", "劉備": "劉備", "この２か月くらい気分が高揚してて、おかげでいろんなことがうまくいってたけど……全部まやかしなんだ……。私なんて必要とされないゴミクズ……はぁ、赤壁に沈んじゃいたい": "這兩個月來我一直都很興奮，拜此所賜很多事情都進展得很順利……但全都是假象……我是個沒人需要的垃圾……唉，好想沉到赤壁去", "たぶん今日でお別れだね、人間さん。もう私、生きていくすべての気力を失ったから。きっと会うことは……": "今天大概就是我們分別的日子了，人類君。我已經失去了活下去的動力。我們肯定不會再見面……", "あっ！　そ、そっか、そうだよね！　仮の話だもんね！　一緒に行ってくれるよね、バブミビーチ！": "啊！ 對、對哦，也是呢！ 只是假設嘛！ 你會跟我一起去吧，巴布米海灘！", "おっっっも": "好——重", "ポセイドン": "波賽頓", "しかし、ふたりとも知ってる子なんですよね？　そういう性格だとわかってたのに、確認を怠ってダブルブッキングしたわけですから……": "不過，你們兩個都是熟人吧？ 明明知道對方是這種性格，卻疏於確認，導致時間衝突了……", "ワダツミ": "和津津見", "自業自得の見本だな": "自作自受的典範呢", "トリアイナ": "特里艾達", "そういう二股みたいなことして、海に沈められてきた男がどれだけいると思ってるのかしらね": "你知不知道有多少男人因爲這種腳踏兩隻船的行爲而沉入大海啊", "オケアノス": "俄刻阿諾斯", "ただでさえ、水はディマイトを引き寄せやすいんです。海みたいな大量に水がある場は、当然ディマイトの温床……この世ならざるものもいるかもしれませんよ？": "水本來就很容易吸引惡之力。像大海這種有大量的水的地方，當然就是惡之力的溫牀……說不定會有不屬於這個世界的東西哦？", "あら、人間さんったら怖くなっちゃったみたいね": "哎呀，人類君好像害怕了呢", "まあまあ。あたしが何とかしてあげるからさ。そのかわり……せっかくのバカンスだから、ちょっと恋人になってくれない？": "好啦好啦，我會想辦法的。作爲交換……難得你這麼笨，能不能當我的男朋友？", "き、汚いですね、人間さん様！　口に含んだ飲み物を吹かないでください！　あと、いつの間に口に含んだんですかそれは！": "你、你太卑鄙了，人類君大人！請不要把嘴裏的飲料噴出來！還有，你什麼時候含在嘴裏的！", "だいじょーぶ、ちょっとデートしてくれるだけでいいのよ♪　ほらもう見えてきたっ、新リン島！": "沒事沒事，只要稍微約會一下就行了♪ 看，新琳島已經近在眼前了！"}