{"澱んだ水は清らかさを取り戻した": "澱積的水恢復了清澈", "アルレーシャ": "雙魚阿錄夏", "曇りなき晴天、心も晴れやか": "晴空萬里，心曠神怡", "アルファーグ": "雙魚阿露法", "ふう……無事に殲滅できましたね": "呼……平安無事地殲滅了呢", "カプリコーン": "摩羯座", "しかし、見たこともない魔物でしたね。人間さん様が一緒でよかった": "但是，是從未見過的魔物呢。和人類君大人在一起真是太好了", "サジタリウス": "人馬座", "そうだよね～。 おにーちゃんが許可してくれないと、本来の力を出せないもんね、わたしたち": "是啊～。要是沒有哥哥的許可，我們就無法發揮原本的力量了呢", "キャンサー": "巨蟹座", "あくまでも仮釈放、 妥当な措置なのだとは思うけどこういう、いざというときは不便だわ": "說到底只是假釋， 我覺得這是妥當的措施，但在這種緊急情況下很不方便呢", "ジャッジメント": "天秤座", "まあ、そこは我慢してもらわないとなぁ…… あっ、そうだ。みんな、ちょっと来てくれないか": "嗯，這點就請忍耐一下吧…… 啊，對了。大家，能過來一下嗎", "人間さん": "人類君", "えっ、いまからですか？": "哎，現在嗎？", "アクエリアス": "寶瓶座", "みんなのところを訪ねたのも、その用件があったからなんだ。 町長さんが用意してくれたんだよ": "我會去拜訪大家，也是因爲有這件事。 是鎮長先生準備的哦", "いやあ、大変お待たせしました。ついに完成しましたぞ！": "哎呀，讓各位久等了。終於完成了哦！", "町長": "鎮長", "わたしたちの衣装も作ってくださってたんですね……！うわあ、可愛い……♪": "還爲我們製作了衣服呢……！哇啊，好可愛……♪", "で、でも！うっかりこれで串カツ食べてソースこぼしたり、 スパゲティ食べててミートソース飛ばしたり、カレーうどん食べてて…… いやああぁぁぁっ！？": "但，但是！要是不小心用這個喫炸串，讓醬汁滴下來， 喫意大利麪的時候讓肉醬飛濺，喫咖喱烏冬的時候…… 不行啊啊啊啊啊！？", "それはシンプルに気を付けなさいよ": "那就簡單地注意一下吧", "タウルス": "金牛座", "紙エプロンあるところも多いでしょ": "很多地方都有紙圍裙吧", "ヴァルゴ": "處女座", "本当にありがとうございます、町長さん": "真是太感謝了，鎮長先生", "お近づきの印にと用意したものでしたが、期せずして魔物を討伐いただいた 直後となって、なんだか表彰式のようですな": "我準備這些衣服本來是想作爲友誼的象徵，沒想到你們剛討伐完魔物，感覺就像在開表彰大會一樣", "みんなよく似合ってるわよ！": "大家穿起來都很好看！", "町民１": "鎮民1", "おねえちゃんたち、かわいい～！": "大姐姐們，好可愛～！", "町民２": "鎮民2", "装いは心の色も変える": "裝束會改變心靈的顏色", "すべての星が輝きを生み出す": "所有星星都會綻放光芒", "だよね～。おそろい、うれしいね～": "就是啊～。大家都穿一樣的衣服，好開心～", "そうね…… 全員で揃って新しい服を作ってもらえるなんて、うれしいことなのだけど……": "是啊…… 大家一起穿新衣服，確實很開心……", "だけど～？": "但是～？", "胸元がきつい……": "胸口好緊……", "わたしもそんなふうに、おっぱいレディになりたいな～": "我也想變成大胸姐姐～", "町民３": "鎮民3", "牛乳をたくさん飲みなさい": "多喝點牛奶吧", "そんなシンプルな方法であんなになるんですか……？": "那麼簡單就能變成那樣嗎……？", "ジェミニ": "雙子座", "あんな、って何よ！聞こえてるからね、ジェミニ！": "那樣是什麼意思！我聽到了哦，雙子座！", "い、いえ、うらやましいんですよ！？": "不，不是，我是很羨慕啊！？", "乳なんて大きくたって得しないわよ。夏場は暑いし、重くて肩こるし": "胸部大又沒什麼好處。夏天會很熱，又重又容易肩膀痠痛", "皆さん、そういうことは言いますよねぇ。もう手で持った方がいいんじゃないですか": "大家都會這麼說呢。乾脆用手拿着算了", "オフィウクス": "蛇遣座", "あっ！": "啊！", "ぷんっ！": "噗！", "ボタンが飛んだ……！": "按鈕飛出去了……！", "町民４": "鎮民4", "なんてこった……": "天哪……", "そこの男ども！前かがみになるのはやめなさいよ！ヘンタイ！": "那些男人！別再把身子往前傾了！變態！", "返す言葉もない": "無言以對"}