{"ふー、リハお疲れ様です。あとは本番を待つだけですね": "呼，彩排辛苦了。接下来就等正式上场了", "マハー": "玛哈", "うちのライブハウスでカラカノが演るなんて、久しぶりだねえ": "你们好久没来我们家的livehouse演出了啊", "スタッフ": "工作人员", "こちらには昔からお世話になってますもんね。それこそサプタラットナの時より前でしょうか": "我们从以前开始就经常来这边演出。应该比萨普塔拉特纳的时候还要早吧", "マハーたち７人揃ってやってた『サプタラットナ』ってバンドより、更に前？そんな時代もあったのね": "比玛哈你们七个人一起组的“萨普塔拉特纳”还要早？原来还有那样的时代啊", "シンデレラ": "仙杜瑞拉", "……最初から７人組だったのかと": "……原来一开始就是七人组啊", "ヴェルメリオ": "威尔梅里奥", "もとはイロハと２人で活動してたんです。あの頃からイロハとはケンカばかりでしたけど": "最开始是和伊吕波两个人一起活动的。虽然从那个时候开始就经常和伊吕波吵架", "えっ！？元『サプタラットナ』メンバーで一番仲悪くて、解散の理由もあなたたち２人だと思ってたんだけど": "诶！？我还以为你们是“萨普塔拉特纳”成员中关系最差的，解散的原因也是你们两个呢", "そうなんですけど、音楽は認めあってたんですよね〜。そのあとヴァイシュラが入って、だいぶ雰囲気は落ち着きましたけど": "是这样没错，但我们还是认可彼此的音乐的。之后瓦伊休拉加入，气氛才稳定下来", "……そこから人数が増えて『サプタラットナ』になったんだね": "……然后人数增加，就变成了“萨普塔拉特纳”啊", "今はまた、カラカノとBeB、それにケーシがソロって分かれちゃいましたけど、本当はあの子たちのことは心配なんですよね": "现在又分成了卡拉卡诺和BeB，还有凯西的单人活动，其实我还是很担心他们的", "そりゃあ、元は仲間だったんだもんね": "那也是，毕竟原本是同伴嘛", "顔を合わせるとケンカになりますけど、だからって嫌ってるわけでもないですし": "虽然一见面就会吵架，但也不是讨厌他们", "……特にケーシは心配だね": "……特别是凯西，让人很担心呢", "まあ、心配してるなんて聞かれたら、それはそれでまたケンカになっちゃうんですけど": "不过，要是被他们知道我在担心他们，又会吵起来的", "やっぱりリーダー気質なのかしらね、マハーは。しっかりしてるし": "果然玛哈有队长气质呢。很可靠", "いえいえ、わたくしなんて、そこまで言っていただけるほどじゃないですよ": "不不，我还没有可靠到那种程度啦", "飼ってたハムスターが逃げたときなんか、ずっと泣いてたもんなあ": "养的仓鼠跑掉的时候，你一直哭个不停呢", "え、ちょ、やだっ。そんな昔の話やめてくださいっ": "咦，等，讨厌。别提那么久以前的事啦", "……あ、珍しく慌ててる": "……啊，难得看到她慌张的样子"}